{
    "name": "Maple AI",
    "type": "MESSAGING",
    "status": "BETA",
    "description": "Described as 'Signal for AI,' this project focuses on privacy-preserving, end-to-end encrypted AI interactions where users can pay with Bitcoin.",
    "version": "N/A",
    "docsUrl": "https://maple.ai",
    "repoUrl": "N/A",
    "features": [
        "Private AI",
        "E2E Encryption",
        "Bitcoin Payments"
    ],
    "stats": {
        "downloads": "N/A",
        "stars": "N/A",
        "dependents": "N/A"
    },
    "installCommand": "N/A"
}